LICENSE
MANIFEST.in
README.md
setup.py
NlpToolkit_Sampling_Cy.egg-info/PKG-INFO
NlpToolkit_Sampling_Cy.egg-info/SOURCES.txt
NlpToolkit_Sampling_Cy.egg-info/dependency_links.txt
NlpToolkit_Sampling_Cy.egg-info/top_level.txt
Sampling/Bootstrap.c
Sampling/Bootstrap.pxd
Sampling/Bootstrap.pyx
Sampling/CrossValidation.c
Sampling/CrossValidation.pxd
Sampling/CrossValidation.pyx
Sampling/KFoldCrossValidation.c
Sampling/KFoldCrossValidation.pxd
Sampling/KFoldCrossValidation.pyx
Sampling/StratifiedKFoldCrossValidation.c
Sampling/StratifiedKFoldCrossValidation.pxd
Sampling/StratifiedKFoldCrossValidation.pyx
Sampling/__init__.py
nlptoolkit_sampling_cy.egg-info/PKG-INFO
nlptoolkit_sampling_cy.egg-info/SOURCES.txt
nlptoolkit_sampling_cy.egg-info/dependency_links.txt
nlptoolkit_sampling_cy.egg-info/top_level.txt