Metadata-Version: 2.4
Name: nlptoolkit-sampling-cy
Version: 1.0.8
Summary: Data sampling library
Home-page: https://github.com/StarlangSoftware/Sampling-Cy
Author: olcaytaner
Author-email: olcay.yildiz@ozyegin.edu.tr
License-File: LICENSE
Dynamic: author
Dynamic: author-email
Dynamic: description
Dynamic: description-content-type
Dynamic: home-page
Dynamic: license-file
Dynamic: summary
